setup.py
clui/__init__.py
clui/clui.py
clui.egg-info/PKG-INFO
clui.egg-info/SOURCES.txt
clui.egg-info/dependency_links.txt
clui.egg-info/requires.txt
clui.egg-info/top_level.txt