Metadata-Version: 1.0
Name: clui
Version: 1.0
Summary: A customizable command line user interface.
Home-page: https://github.com/doubledubba/clui
Author: Luis Naranjo
Author-email: luisnaranjo733@hotmail.com
License: GNU GPL3
Keywords: CLUI clui ui command line user interface
Platform: any
